rxnoptgoaliteragent/__init__.py
rxnoptgoaliteragent/entry_point.py
rxnoptgoaliteragent/agent/__init__.py
rxnoptgoaliteragent/agent/rxn_opt_goal_iter_agent.py
rxnoptgoaliteragent/data_model/__init__.py
rxnoptgoaliteragent/data_model/iris.py
rxnoptgoaliteragent/data_model/ontogoal.py
rxnoptgoaliteragent/kg_operations/__init__.py
rxnoptgoaliteragent/kg_operations/sparql_client.py
rxnoptgoaliteragent/tests/__init__.py
rxnoptgoaliteragent/tests/conftest.py
rxnoptgoaliteragent/tests/test_kg_sparql_client.py
rxnoptgoaliteragent/tests/test_rxn_opt_goal_iter.py
rxnoptgoaliteragent/tests/test_triples/goal_iter.ttl
rxnoptgoaliteragent/tests/test_triples/plan_step_agent.ttl
rxnoptgoaliteragent-1.2.0.dist-info/METADATA
rxnoptgoaliteragent-1.2.0.dist-info/WHEEL
rxnoptgoaliteragent-1.2.0.dist-info/top_level.txt
rxnoptgoaliteragent-1.2.0.dist-info/RECORD
