Metadata-Version: 2.1
Name: rxnoptgoaliteragent
Version: 1.2.0
Summary: rxnoptgoaliteragent is capable of conducting one iteration of pursuring the reaction optimisation goal as part of The World Avatar project.
Home-page: https://github.com/cambridge-cares/TheWorldAvatar/tree/main/Agents/RxnOptGoalIterAgent
Author: Jiaru Bai
Author-email: jb2197@cam.ac.uk
License: MIT
Requires-Python: >=3.8
Requires-Dist: pyderivationagent (>=1.4.3)
Requires-Dist: pandas
Requires-Dist: pydantic (==1.9.0)
Requires-Dist: chemistry-and-robots (>=1.6.0)
Provides-Extra: dev
Requires-Dist: testcontainers (>=3.4.2) ; extra == 'dev'
Requires-Dist: pytest (>=6.2.3) ; extra == 'dev'
Requires-Dist: pytest-docker-compose (>=3.2.1) ; extra == 'dev'
Requires-Dist: pytest-rerunfailures (>=10.2) ; extra == 'dev'
